eventize/__init__.py
eventize/metadata.py
eventize/api/__init__.py
eventize/api/constructors.py
eventize/api/decorators.py
eventize/attribute/__init__.py
eventize/attribute/descriptor.py
eventize/attribute/event.py
eventize/attribute/handler.py
eventize/attribute/value.py
eventize/descriptors/__init__.py
eventize/descriptors/handler.py
eventize/descriptors/handlerValue.py
eventize/descriptors/named.py
eventize/descriptors/value.py
eventize/descriptors/wrappers.py
eventize/doc/Makefile
eventize/doc/make.bat
eventize/doc/source/advanced usage.rst
eventize/doc/source/basic usage.rst
eventize/doc/source/conf.py
eventize/doc/source/development.rst
eventize/doc/source/index.rst
eventize/doc/source/installation.rst
eventize/doc/source/introduction.rst
eventize/events/__init__.py
eventize/events/event.py
eventize/events/exceptions.py
eventize/events/handler.py
eventize/events/subject.py
eventize/method/__init__.py
eventize/method/descriptor.py
eventize/method/event.py
eventize/method/handler.py
eventize/method/value.py
eventize/modifiers/__init__.py
eventize/modifiers/descriptors.py
eventize/modifiers/handlers.py
eventize/typing/__init__.py
eventize/typing/descriptors.py
eventize/typing/events.py
eventize/typing/modifiers.py
eventize/typing/stack.py
eventize-0.4.4.dist-info/LICENCE
eventize-0.4.4.dist-info/METADATA
eventize-0.4.4.dist-info/WHEEL
eventize-0.4.4.dist-info/top_level.txt
eventize-0.4.4.dist-info/zip-safe
eventize-0.4.4.dist-info/RECORD
